[
    {
        "description": "Tests description",
        "type": "daily",
        "target": 4,
        "objectives": [
            {
                "type": "kills",
                "value": 4,
                "comparison": "greater"
            },
            {
                "type": "character",
                "value": "muflus",
                "comparison": "equal"
            },
            {
                "type": "result",
                "value": "abandon",
                "comparison": "equal"
            }
        ]
    }
]
